{"vue_3_composition-api.md":"t9QrMDFU","webpack_plugin_compression-webpack-plugin.md":"szc_nHTB","nodejs_packages_http_axios.md":"vPekjgtZ","nodejs_packages_css_less.md":"1mE49S_J","css_box-model.md":"XdvJ1pVG","markdown-examples.md":"dYBxJqyk","nodejs_packages_animation_animejs.md":"wAqTQEPa","nginx_nginx-guide.md":"s92Bsn9X","nodejs_packages_utils_lodash.md":"OKKPRjED","nodejs_packages_document_vditor.md":"nhcKEcbT","webpack_loader_node-sass.md":"j3p_TY7R","nodejs_packages_index.md":"knoKJnRI","nodejs_packages_utils_ramda.md":"jGJ3Zzn8","nodejs_packages_document_x-spreadsheet.md":"X0S9YHIQ","css_css.md":"Ur9AwmRO","browser_google-chrome.md":"2_83JpAj","nodejs_packages_css_postcss.md":"fq3IWa7t","nodejs_packages_http_superagent.md":"IDt6O04T","nodejs_packages_document_docx.md":"r2o2Y23I","webpack_webpack.md":"R0x2Ig-T","nodejs_packages_css_sass.md":"hhlwCkv_","webpack_plugin_webpack-obfuscator.md":"QAc9nYO3","nodejs_packages_date_moment.md":"HRId6xNJ","nodejs_packages_chart_apache-echarts.md":"7sNr7A-n","nodejs_packages_utils_underscorejs.md":"Klsf5PiI","git_github_github-pages.md":"pNQVyT-7","windows_index.md":"Sn5P1I2K","css_specificity.md":"LKyxAnKj","nodejs_packages_date_day.md":"Gl8SCbxf","vue_vite_how-to-migrate-from-vue-cli-to-vite.md":"fuy_cOT5","webpack_plugin_uglifyjs-webpack-plugin.md":"LKRjy8Oq","css_selectors.md":"2XgxsieW","vue_2_jsx.md":"yfrWX7kP","vue_3_options-api.md":"w6JOxd5c","nodejs_npm.md":"cLoKv2h8","nodejs_packages_document_sheetjs.md":"jVDZkCI0","nodejs_packages_document_pdfjs.md":"V-l4d0NH","index.md":"HF3CIQ_2","vue_2_cheatsheet.md":"9rycc2C7","vue_2_render-function.md":"v_Aw0Lyp","git_git-cheatsheet.md":"8kJsoEba"}
